MC_Int/__init__.py
MC_Int/modulo.py
MCInt_ana.arcila1-0.1.0.dist-info/METADATA
MCInt_ana.arcila1-0.1.0.dist-info/WHEEL
MCInt_ana.arcila1-0.1.0.dist-info/top_level.txt
MCInt_ana.arcila1-0.1.0.dist-info/RECORD
