Metadata-Version: 2.1
Name: MCInt-ana.arcila1
Version: 0.1.0
Summary: libreria de integración con Monte Carlo
Home-page: UNKNOWN
Author: Ana Maria
Author-email: aarcila01@gmail.com
License: MIT
Platform: UNKNOWN
Requires-Python: >=3.9.12
Requires-Dist: numpy (==1.26.1)
Requires-Dist: matplotlib (==3.5.3)
Requires-Dist: scipy (==1.7.3)
